MAIN.py
HyperTech_STT-0.1.dist-info/METADATA
HyperTech_STT-0.1.dist-info/WHEEL
HyperTech_STT-0.1.dist-info/top_level.txt
HyperTech_STT-0.1.dist-info/RECORD
